<?xml version="1.0" encoding="UTF-8"?><TestSuites formatVersion="1.0" toolName="C++Test">
<TestSuite context="Calculator/Calculator/源文件/Calculator.cpp" name="TestSuite_Calculator_cpp_a3ed44a1">
<HeaderFile name="C:\Users\ruiking\Documents\Visual Studio 2010\Projects\Calculator\Calculator\tests\autogenerated\源文件\TestSuite_Calculator_cpp.cpp"/>
<SourceFile name=""/>
<TestCases>
<TestCase name="test_add_1"/>
<TestCase name="test_add_10"/>
<TestCase name="test_add_2"/>
<TestCase name="test_add_3"/>
<TestCase name="test_add_4"/>
<TestCase name="test_add_5"/>
<TestCase name="test_add_6"/>
<TestCase name="test_add_7"/>
<TestCase name="test_add_8"/>
<TestCase name="test_add_9"/>
<TestCase name="test_divide_1"/>
<TestCase name="test_divide_10"/>
<TestCase name="test_divide_2"/>
<TestCase name="test_divide_3"/>
<TestCase name="test_divide_4"/>
<TestCase name="test_divide_5"/>
<TestCase name="test_divide_6"/>
<TestCase name="test_divide_7"/>
<TestCase name="test_divide_8"/>
<TestCase name="test_divide_9"/>
<TestCase name="test_minus_1"/>
<TestCase name="test_minus_10"/>
<TestCase name="test_minus_2"/>
<TestCase name="test_minus_3"/>
<TestCase name="test_minus_4"/>
<TestCase name="test_minus_5"/>
<TestCase name="test_minus_6"/>
<TestCase name="test_minus_7"/>
<TestCase name="test_minus_8"/>
<TestCase name="test_minus_9"/>
<TestCase name="test_multiply_1"/>
<TestCase name="test_multiply_10"/>
<TestCase name="test_multiply_2"/>
<TestCase name="test_multiply_3"/>
<TestCase name="test_multiply_4"/>
<TestCase name="test_multiply_5"/>
<TestCase name="test_multiply_6"/>
<TestCase name="test_multiply_7"/>
<TestCase name="test_multiply_8"/>
<TestCase name="test_multiply_9"/>
<TestCase name="test_wmain_1"/>
<TestCase name="test_wmain_10"/>
<TestCase name="test_wmain_2"/>
<TestCase name="test_wmain_3"/>
<TestCase name="test_wmain_4"/>
<TestCase name="test_wmain_5"/>
<TestCase name="test_wmain_6"/>
<TestCase name="test_wmain_7"/>
<TestCase name="test_wmain_8"/>
<TestCase name="test_wmain_9"/>
</TestCases>
</TestSuite>
</TestSuites>
